<?xml version="1.0" encoding="utf-8" ?><dwsync><file name=".DS_Store" server="go2lighthouse.org" local="3440072520" remote="389741192898369352" /><file name="config.php" server="go2lighthouse.org" local="3440181960" remote="389741192898478792" /><file name="getevent.php" server="go2lighthouse.org" local="3440092500" remote="389741192898389332" /><file name="getevents.php" server="go2lighthouse.org" local="3443345592" remote="502703711869279868" /><file name="getnotices.php" server="go2lighthouse.org" local="3440307480" remote="389741192898604312" /><file name="getnotice.php" server="go2lighthouse.org" local="3441888900" remote="389741192900185732" /><file name="getprayerrequests.php" server="go2lighthouse.org" local="3443476841" remote="399080221329792784" /><file name="getprayer.php" server="go2lighthouse.org" local="3443477150" remote="509807381618565180" /></dwsync>