<?xml version="1.0" encoding="utf-8" ?><dwsync><file name="eventdetails.js" server="go2lighthouse.org" local="3442155720" remote="502624495491293384" /><file name="eventlist.js" server="go2lighthouse.org" local="3441880740" remote="502624495491018404" /><file name="jquery.js" server="go2lighthouse.org" local="3440072520" remote="502624495489210184" /><file name="jquery.mobile-1.0rc1.min.js" server="go2lighthouse.org" local="3440072520" remote="502624495489210184" /><file name="noticelist.js" server="go2lighthouse.org" local="3441888060" remote="502624495491025724" /><file name="jqm.page.params.js" server="go2lighthouse.org" local="3441880380" remote="502624495491018044" /><file name="noticedetails.js" server="go2lighthouse.org" local="3441890100" remote="502624495491027764" /><file name="prayerlist.js" server="go2lighthouse.org" local="3443476963" remote="470932756449140616" /><file name="prayerdetails.js" server="go2lighthouse.org" local="3443477094" remote="386017920112599040" /></dwsync>